analiz/__init__.py
analiz/analiz.py
metinanaliz-1.1.6.dist-info/LICENSE.txt
metinanaliz-1.1.6.dist-info/METADATA
metinanaliz-1.1.6.dist-info/WHEEL
metinanaliz-1.1.6.dist-info/top_level.txt
metinanaliz-1.1.6.dist-info/RECORD
