Metadata-Version: 2.1
Name: metinanaliz
Version: 1.1.6
Summary: Türkçe Metin Analizi
Home-page: https://github.com/karanba/MetinAnaliz
Author: Altay Karakuş
Author-email: altaykarakus@gmail.com
License: MIT
Keywords: analiz,metin,türkçe
Platform: UNKNOWN
Classifier: Programming Language :: Python :: 3
Classifier: License :: OSI Approved :: MIT License
Classifier: Operating System :: OS Independent
Requires-Python: >=3.6
